cymru/__init__.py
cymru/cymru.py
cymru-0.1.0.dist-info/licenses/LICENSE
cymru-0.1.0.dist-info/METADATA
cymru-0.1.0.dist-info/WHEEL
cymru-0.1.0.dist-info/top_level.txt
cymru-0.1.0.dist-info/RECORD
